{
  "sprint": "F206AI",
  "timestamp": "2026-05-01T12:54:00Z",
  "scope": "graph_ecosystem_authority_and_write_path_seal",
  "authority_matrix": {
    "active_truth_writer": {
      "module": "graph/quantum_pathfinder.py",
      "class": "DuckPGQGraph",
      "backend": "DuckDB",
      "write_methods": ["add_ioc", "add_relation"],
      "canonical": true,
      "deprecation_risk": "NONE — active truth store for scheduler accumulation path (Sprint F226)",
      "callers": [
        "runtime/sprint_scheduler.py::_accumulate_findings_to_graph (line ~7090)",
        "runtime/sprint_scheduler.py::graph_service.upsert_ioc_batch (line ~7128)"
      ]
    },
    "facade": {
      "module": "knowledge/graph_service.py",
      "class": "module-level functions",
      "write_methods": ["upsert_ioc", "upsert_relation", "upsert_identity_edge", "upsert_ioc_batch"],
      "canonical": false,
      "deprecation_risk": "NONE — facade delegates to DuckPGQGraph",
      "notes": "reset_session() exists at line ~152 — called at sprint teardown. _get_graph() lazy-inits DuckPGQGraph."
    },
    "standalone_truth_store": {
      "module": "knowledge/ioc_graph.py",
      "class": "IOCGraph",
      "backend": "Kuzu",
      "write_methods": ["upsert_ioc", "buffer_ioc", "upsert_ioc_batch", "add_relation", "export_stix_bundle"],
      "canonical": false,
      "deprecation_risk": "NONE — valid standalone truth store, not active in scheduler accumulation path",
      "notes": "IOCGraph remains a valid standalone truth store. Not the active target for _accumulate_findings_to_graph."
    },
    "capability_gate": {
      "module": "knowledge/graph_attachment.py",
      "class": "GraphAttachmentStore",
      "write_methods": ["inject_graph (capability-checked)", "inject_truth_write_graph"],
      "canonical": false,
      "deprecation_risk": "NONE — explicit capability/authority check in inject_graph",
      "notes": "inject_graph docstring: 'STORE IS NOT GRAPH TRUTH OWNER'. Capability check at line 64."
    },
    "sprint_facts_store": {
      "module": "knowledge/duckdb_store.py",
      "class": "DuckDBShadowStore",
      "write_methods": ["inject_graph (DEPRECATED — delegates to GraphAttachmentStore)"],
      "canonical": false,
      "deprecation_risk": "NONE — explicitly labeled DEPRECATED in docstring (Sprint F222)",
      "notes": "inject_graph() marked DEPRECATED, delegates entirely to _graph_store().inject_graph(). NOT graph authority."
    },
    "reasoning_overlay_read_only": {
      "module": "coordinators/graph_coordinator.py",
      "class": "GraphCoordinator",
      "write_methods": [],
      "canonical": false,
      "deprecation_risk": "NONE — read-only overlay",
      "notes": "No direct writes. Delegates to graph_service facade."
    },
    "reasoning_overlay_analytics": {
      "module": "graph/quantum_pathfinder.py",
      "class": "QuantumInspiredPathFinder",
      "write_methods": [],
      "canonical": false,
      "deprecation_risk": "NONE — read-only analytics path",
      "notes": "Uses DuckPGQGraph for RAG-style queries. Not a truth writer."
    },
    "deprecated_donor_modules": {
      "knowledge/graph_layer.py": {
        "class": "KnowledgeGraphLayer",
        "write_methods": ["add_entry"],
        "status": "DEPRECATED — 130 lines, no active call sites found",
        "deprecation_risk": "LOW — add_entry not called in production",
        "evidence": "No imports in sprint_scheduler, graph_service, or production paths"
      },
      "knowledge/context_graph.py": {
        "class": "ContextGraph",
        "write_methods": ["add_node", "add_edge"],
        "status": "DEPRECATED — 54 lines, only imported by legacy/autonomous_orchestrator.py",
        "deprecation_risk": "LOW — legacy import only",
        "evidence": "Imported only in legacy/ directory (pre-F195 refactor)"
      },
      "knowledge/graph_rag.py": {
        "class": "GraphRAG",
        "write_methods": [],
        "status": "ACTIVE-READ — 2590 lines, RAG/similarity search only",
        "deprecation_risk": "NONE — read-only, no upsert/add methods",
        "evidence": "Zero write methods found. Pure read RAG pipeline."
      },
      "knowledge/persistent_layer.py": {
        "class": "N/A (stub)",
        "write_methods": [],
        "status": "DEPRECATED STUB — 25 lines, generated from bytecode",
        "deprecation_risk": "NONE — stub only, no real code",
        "evidence": "Stub file forwarding to legacy.persistent_layer"
      },
      "legacy/persistent_layer.py": {
        "status": "OUT OF SCOPE — outside universal/ boundary",
        "deprecation_risk": "UNKNOWN — not scanned per scope rule"
      }
    }
  },
  "write_path_call_sites": {
    "canonical_upsert_ioc_batch": [
      {
        "caller": "runtime/sprint_scheduler.py",
        "line": 7090,
        "method": "_accumulate_findings_to_graph",
        "target": "graph_service.upsert_ioc_batch",
        "authority": "DuckPGQGraph (DuckDB) — ACTIVE TRUTH (Sprint F226)"
      },
      {
        "caller": "runtime/sprint_scheduler.py",
        "line": 7128,
        "method": "_accumulate_findings_to_graph",
        "target": "DuckPGQGraph.upsert_ioc_batch (via graph_service)",
        "authority": "DuckPGQGraph — ACTIVE TRUTH"
      }
    ],
    "buffer_ioc_pivot": [
      {
        "caller": "runtime/sprint_scheduler.py",
        "line": 10696,
        "method": "_buffer_ioc_pivot",
        "target": "self._ioc_graph.add_relation",
        "authority": "DuckPGQGraph — self._ioc_graph is DuckPGQGraph instance"
      },
      {
        "caller": "runtime/sprint_scheduler.py",
        "line": 10704,
        "method": "_buffer_ioc_pivot",
        "target": "_pivot_ioc_graph.buffer_ioc",
        "authority": "IOCGraph (Kuzu) — _pivot_ioc_graph is IOCGraph (Kuzu) injected via inject_ioc_graph"
      }
    ],
    "buffer_ioc": [
      {
        "caller": "runtime/sprint_scheduler.py",
        "line": 10996,
        "method": "buffer_ioc",
        "target": "self._ioc_graph.add_relation",
        "authority": "DuckPGQGraph"
      }
    ]
  },
  "reset_session_verification": {
    "exists": true,
    "location": "knowledge/graph_service.py:152",
    "call_site": "runtime/sprint_scheduler.py:12103",
    "status": "VERIFIED — reset_session called at sprint teardown"
  },
  "duckdb_shadow_store_gate": {
    "inject_graph_capability_required": false,
    "inject_graph_deprecated": true,
    "deprecation_note": "DEPRECATED (Sprint F222): delegates to GraphAttachmentStore.inject_graph()",
    "capability_gate_lives_in": "GraphAttachmentStore.inject_graph (graph_attachment.py:64)",
    "status": "UPDATED — DuckDBShadowStore.inject_graph is DEPRECATED; capability gate moved to GraphAttachmentStore"
  },
  "deprecated_modules_verdict": {
    "graph_layer": "CANNOT SILENTLY BECOME ACTIVE — add_entry() has zero production call sites",
    "context_graph": "CANNOT SILENTLY BECOME ACTIVE — only referenced in legacy/ directory",
    "graph_rag": "SAFE — read-only RAG, zero write methods",
    "persistent_layer": "STUB — no real code, forwarding to legacy/"
  },
  "aborted_conditions": {
    "live_graph_db_mutation": "PREVENTED — tests use MagicMock/AsyncMock only",
    "network": "NOT USED",
    "model_load": "NOT USED",
    "broad_rewrite": "NOT DONE — only VERDICT comments added to source files"
  }
}